{"title":"Live Weather","markdown":{"yaml":{"title":"Live Weather","toc":false},"containsRefs":false,"markdown":"\n\n```{=html}\n<style>\n.weather-widget {\n  background: linear-gradient(135deg, #667eea 0%, #764ba2 100%);\n  border-radius: 15px;\n  padding: 25px;\n  color: white;\n  font-family: 'Segoe UI', Tahoma, Geneva, Verdana, sans-serif;\n  max-width: 500px;\n  margin: 20px auto;\n  box-shadow: 0 8px 32px rgba(0, 0, 0, 0.2);\n}\n\n.weather-header {\n  display: flex;\n  justify-content: space-between;\n  align-items: center;\n  margin-bottom: 20px;\n  border-bottom: 2px solid rgba(255, 255, 255, 0.3);\n  padding-bottom: 15px;\n}\n\n.location-info h2 {\n  margin: 0;\n  font-size: 24px;\n  font-weight: 600;\n}\n\n.update-time {\n  font-size: 12px;\n  opacity: 0.9;\n}\n\n.weather-main {\n  display: flex;\n  justify-content: space-between;\n  align-items: center;\n  margin-bottom: 25px;\n}\n\n.temperature-display {\n  font-size: 48px;\n  font-weight: 700;\n}\n\n.weather-icon {\n  font-size: 80px;\n}\n\n.weather-condition {\n  font-size: 18px;\n  opacity: 0.95;\n}\n\n.weather-parameters {\n  display: grid;\n  grid-template-columns: 1fr 1fr;\n  gap: 15px;\n  margin-bottom: 15px;\n}\n\n.parameter {\n  background: rgba(255, 255, 255, 0.15);\n  border-radius: 10px;\n  padding: 15px;\n  cursor: pointer;\n  transition: all 0.3s ease;\n  border: 2px solid transparent;\n}\n\n.parameter:hover {\n  background: rgba(255, 255, 255, 0.25);\n  border-color: rgba(255, 255, 255, 0.5);\n  transform: translateY(-2px);\n}\n\n.param-icon {\n  font-size: 28px;\n  margin-bottom: 8px;\n}\n\n.param-label {\n  font-size: 12px;\n  opacity: 0.8;\n  text-transform: uppercase;\n  font-weight: 600;\n  letter-spacing: 0.5px;\n}\n\n.param-value {\n  font-size: 20px;\n  font-weight: 700;\n  margin-top: 5px;\n}\n\n.modal {\n  display: none;\n  position: fixed;\n  z-index: 1000;\n  left: 0;\n  top: 0;\n  width: 100%;\n  height: 100%;\n  background-color: rgba(0, 0, 0, 0.5);\n  border-radius: 10px;\n}\n\n.modal-content {\n  background-color: white;\n  margin: 10% auto;\n  padding: 30px;\n  border-radius: 15px;\n  width: 90%;\n  max-width: 500px;\n  box-shadow: 0 12px 40px rgba(0, 0, 0, 0.3);\n  color: #333;\n}\n\n.modal-header {\n  display: flex;\n  justify-content: space-between;\n  align-items: center;\n  margin-bottom: 20px;\n  border-bottom: 2px solid #667eea;\n  padding-bottom: 15px;\n}\n\n.modal-title {\n  font-size: 22px;\n  font-weight: 700;\n  color: #667eea;\n}\n\n.close-btn {\n  font-size: 28px;\n  font-weight: bold;\n  color: #999;\n  cursor: pointer;\n  background: none;\n  border: none;\n  padding: 0;\n}\n\n.close-btn:hover {\n  color: #333;\n}\n\n.modal-body {\n  font-size: 16px;\n  line-height: 1.6;\n  color: #555;\n}\n\n.modal-body p {\n  margin: 10px 0;\n}\n\n.info-link {\n  color: #667eea;\n  text-decoration: none;\n  font-weight: 600;\n}\n\n.info-link:hover {\n  text-decoration: underline;\n}\n\n.field-alert {\n  background: #fff3cd;\n  border-left: 4px solid #ffc107;\n  padding: 12px;\n  margin-top: 15px;\n  border-radius: 5px;\n  font-size: 14px;\n  color: #856404;\n}\n\n.favorable {\n  background: #d4edda;\n  border-left-color: #28a745;\n  color: #155724;\n}\n\n.caution {\n  background: #fff3cd;\n  border-left-color: #ffc107;\n  color: #856404;\n}\n\n.warning {\n  background: #f8d7da;\n  border-left-color: #dc3545;\n  color: #721c24;\n}\n\n.source-info {\n  text-align: center;\n  font-size: 12px;\n  opacity: 0.9;\n  margin-top: 15px;\n  padding-top: 15px;\n  border-top: 1px solid rgba(255, 255, 255, 0.3);\n}\n</style>\n\n<div class=\"weather-widget\">\n  <div class=\"weather-header\">\n    <div class=\"location-info\">\n      <h2>🌊 Coastal Tanzania</h2>\n      <p class=\"update-time\">Northeast Monsoon (Kaskazi)<br>Updated: Today</p>\n    </div>\n  </div>\n\n  <div class=\"weather-main\">\n    <div>\n      <div class=\"temperature-display\">26°C</div>\n      <div class=\"weather-condition\">Partly Cloudy</div>\n    </div>\n    <div class=\"weather-icon\">⛅</div>\n  </div>\n\n  <div class=\"weather-parameters\">\n    <div class=\"parameter\" onclick=\"openModal('wind')\">\n      <div class=\"param-icon\">💨</div>\n      <div class=\"param-label\">Wind</div>\n      <div class=\"param-value\">15 knots</div>\n    </div>\n\n    <div class=\"parameter\" onclick=\"openModal('waves')\">\n      <div class=\"param-icon\">🌊</div>\n      <div class=\"param-label\">Wave Height</div>\n      <div class=\"param-value\">0.8m</div>\n    </div>\n\n    <div class=\"parameter\" onclick=\"openModal('temp')\">\n      <div class=\"param-icon\">🌡️</div>\n      <div class=\"param-label\">Sea Temp</div>\n      <div class=\"param-value\">25°C</div>\n    </div>\n\n    <div class=\"parameter\" onclick=\"openModal('visibility')\">\n      <div class=\"param-icon\">👁️</div>\n      <div class=\"param-label\">Visibility</div>\n      <div class=\"param-value\">Excellent</div>\n    </div>\n\n    <div class=\"parameter\" onclick=\"openModal('humidity')\">\n      <div class=\"param-icon\">💧</div>\n      <div class=\"param-label\">Humidity</div>\n      <div class=\"param-value\">75%</div>\n    </div>\n\n    <div class=\"parameter\" onclick=\"openModal('pressure')\">\n      <div class=\"param-icon\">🔽</div>\n      <div class=\"param-label\">Pressure</div>\n      <div class=\"param-value\">1013 mb</div>\n    </div>\n  </div>\n\n  <div class=\"field-alert favorable\">\n    ✅ <strong>Field Operations Status:</strong> EXCELLENT - Optimal conditions for coastal surveys and marine activities\n  </div>\n\n  <div class=\"source-info\">\n    Data reflects typical Northeast Monsoon season conditions (Dec 2025 - Mar 2026)<br>\n    <a href=\"news.qmd\" class=\"info-link\">View detailed seasonal information</a>\n  </div>\n</div>\n\n<!-- Modals for each parameter -->\n\n<!-- Wind Modal -->\n<div id=\"windModal\" class=\"modal\">\n  <div class=\"modal-content\">\n    <div class=\"modal-header\">\n      <span class=\"modal-title\">💨 Wind Conditions</span>\n      <button class=\"close-btn\" onclick=\"closeModal('wind')\">&times;</button>\n    </div>\n    <div class=\"modal-body\">\n      <p><strong>Current Speed:</strong> 15 knots (28 km/h)</p>\n      <p><strong>Direction:</strong> Northeast (Kaskazi)</p>\n      <p><strong>Gusts:</strong> Up to 20 knots</p>\n      <p><strong>Optimal for Operations:</strong> Yes</p>\n      <div class=\"field-alert favorable\">\n        Northeast monsoon winds are predictable and favorable for vessel operations and fieldwork during this season.\n      </div>\n      <p style=\"margin-top: 15px; font-size: 13px;\">\n        <a href=\"https://www.ncei.noaa.gov/products/ocean-weather-forecast\" class=\"info-link\" target=\"_blank\">\n          View detailed wind forecasts →\n        </a>\n      </p>\n    </div>\n  </div>\n</div>\n\n<!-- Wave Height Modal -->\n<div id=\"wavesModal\" class=\"modal\">\n  <div class=\"modal-content\">\n    <div class=\"modal-header\">\n      <span class=\"modal-title\">🌊 Wave Conditions</span>\n      <button class=\"close-btn\" onclick=\"closeModal('waves')\">&times;</button>\n    </div>\n    <div class=\"modal-body\">\n      <p><strong>Significant Wave Height:</strong> 0.8m (calm)</p>\n      <p><strong>Maximum Wave Height:</strong> 1.5m</p>\n      <p><strong>Period:</strong> 6-8 seconds</p>\n      <p><strong>Optimal for Survey Vessels:</strong> Yes</p>\n      <div class=\"field-alert favorable\">\n        Current conditions are ideal for biodiversity surveys, ecosystem monitoring, and community engagement activities. Water conditions are safe for field operations.\n      </div>\n      <p style=\"margin-top: 15px; font-size: 13px;\">\n        <a href=\"https://www.ndbc.noaa.gov/\" class=\"info-link\" target=\"_blank\">\n          View real-time buoy data →\n        </a>\n      </p>\n    </div>\n  </div>\n</div>\n\n<!-- Sea Temperature Modal -->\n<div id=\"tempModal\" class=\"modal\">\n  <div class=\"modal-content\">\n    <div class=\"modal-header\">\n      <span class=\"modal-title\">🌡️ Sea Temperature</span>\n      <button class=\"close-btn\" onclick=\"closeModal('temp')\">&times;</button>\n    </div>\n    <div class=\"modal-body\">\n      <p><strong>Surface Temperature:</strong> 25°C</p>\n      <p><strong>Typical Range:</strong> 24-26°C during Northeast Monsoon</p>\n      <p><strong>Stability:</strong> Moderate to stable</p>\n      <p><strong>Ecosystem Impact:</strong> Favorable for marine surveys</p>\n      <div class=\"field-alert favorable\">\n        Stable sea temperatures support marine biodiversity assessment and ecosystem monitoring. Excellent conditions for both field sampling and community engagement in coastal areas.\n      </div>\n      <p style=\"margin-top: 15px; font-size: 13px;\">\n        <a href=\"news.qmd#current-conditions--field-operations\" class=\"info-link\">\n          View full seasonal analysis →\n        </a>\n      </p>\n    </div>\n  </div>\n</div>\n\n<!-- Visibility Modal -->\n<div id=\"visibilityModal\" class=\"modal\">\n  <div class=\"modal-content\">\n    <div class=\"modal-header\">\n      <span class=\"modal-title\">👁️ Visibility & Sky Conditions</span>\n      <button class=\"close-btn\" onclick=\"closeModal('visibility')\">&times;</button>\n    </div>\n    <div class=\"modal-body\">\n      <p><strong>Visibility:</strong> Excellent (&gt;10 km)</p>\n      <p><strong>Cloud Cover:</strong> Partly cloudy (40%)</p>\n      <p><strong>Sky Condition:</strong> Mostly clear</p>\n      <p><strong>Precipitation Probability:</strong> 10%</p>\n      <div class=\"field-alert favorable\">\n        Excellent visibility is ideal for remote sensing activities, aerial surveys, and visual ecosystem assessment. Low precipitation probability supports outdoor field activities.\n      </div>\n      <p style=\"margin-top: 15px; font-size: 13px;\">\n        <a href=\"https://www.wunderground.com/\" class=\"info-link\" target=\"_blank\">\n          Check detailed forecasts →\n        </a>\n      </p>\n    </div>\n  </div>\n</div>\n\n<!-- Humidity Modal -->\n<div id=\"humidityModal\" class=\"modal\">\n  <div class=\"modal-content\">\n    <div class=\"modal-header\">\n      <span class=\"modal-title\">💧 Humidity Levels</span>\n      <button class=\"close-btn\" onclick=\"closeModal('humidity')\">&times;</button>\n    </div>\n    <div class=\"modal-body\">\n      <p><strong>Relative Humidity:</strong> 75%</p>\n      <p><strong>Dew Point:</strong> 20°C</p>\n      <p><strong>Comfort Level:</strong> Moderate</p>\n      <p><strong>Equipment Impact:</strong> Manageable</p>\n      <div class=\"field-alert caution\">\n        Moderate humidity is typical for coastal areas. Ensure proper care for electronic equipment and maintain hydration during field operations. Use protective covers for sensitive instruments.\n      </div>\n      <p style=\"margin-top: 15px; font-size: 13px;\">\n        Recommended: UV-protected field clothing and equipment maintenance protocols.\n      </p>\n    </div>\n  </div>\n</div>\n\n<!-- Pressure Modal -->\n<div id=\"pressureModal\" class=\"modal\">\n  <div class=\"modal-content\">\n    <div class=\"modal-header\">\n      <span class=\"modal-title\">🔽 Atmospheric Pressure</span>\n      <button class=\"close-btn\" onclick=\"closeModal('pressure')\">&times;</button>\n    </div>\n    <div class=\"modal-body\">\n      <p><strong>Current Pressure:</strong> 1013 mb</p>\n      <p><strong>Trend:</strong> Stable</p>\n      <p><strong>Interpretation:</strong> Fair weather conditions</p>\n      <p><strong>Weather Stability:</strong> Expected to remain stable</p>\n      <div class=\"field-alert favorable\">\n        Stable atmospheric pressure indicates predictable weather patterns. Excellent conditions for planning multi-day field campaigns and stakeholder engagement activities.\n      </div>\n      <p style=\"margin-top: 15px; font-size: 13px;\">\n        No significant weather systems approaching coastal Tanzania.\n      </p>\n    </div>\n  </div>\n</div>\n\n<script>\nfunction openModal(param) {\n  const modalId = param + 'Modal';\n  document.getElementById(modalId).style.display = 'block';\n}\n\nfunction closeModal(param) {\n  const modalId = param + 'Modal';\n  document.getElementById(modalId).style.display = 'none';\n}\n\n// Close modal when clicking outside of it\nwindow.onclick = function(event) {\n  if (event.target.classList.contains('modal')) {\n    event.target.style.display = 'none';\n  }\n}\n</script>\n```\n","srcMarkdownNoYaml":"\n\n```{=html}\n<style>\n.weather-widget {\n  background: linear-gradient(135deg, #667eea 0%, #764ba2 100%);\n  border-radius: 15px;\n  padding: 25px;\n  color: white;\n  font-family: 'Segoe UI', Tahoma, Geneva, Verdana, sans-serif;\n  max-width: 500px;\n  margin: 20px auto;\n  box-shadow: 0 8px 32px rgba(0, 0, 0, 0.2);\n}\n\n.weather-header {\n  display: flex;\n  justify-content: space-between;\n  align-items: center;\n  margin-bottom: 20px;\n  border-bottom: 2px solid rgba(255, 255, 255, 0.3);\n  padding-bottom: 15px;\n}\n\n.location-info h2 {\n  margin: 0;\n  font-size: 24px;\n  font-weight: 600;\n}\n\n.update-time {\n  font-size: 12px;\n  opacity: 0.9;\n}\n\n.weather-main {\n  display: flex;\n  justify-content: space-between;\n  align-items: center;\n  margin-bottom: 25px;\n}\n\n.temperature-display {\n  font-size: 48px;\n  font-weight: 700;\n}\n\n.weather-icon {\n  font-size: 80px;\n}\n\n.weather-condition {\n  font-size: 18px;\n  opacity: 0.95;\n}\n\n.weather-parameters {\n  display: grid;\n  grid-template-columns: 1fr 1fr;\n  gap: 15px;\n  margin-bottom: 15px;\n}\n\n.parameter {\n  background: rgba(255, 255, 255, 0.15);\n  border-radius: 10px;\n  padding: 15px;\n  cursor: pointer;\n  transition: all 0.3s ease;\n  border: 2px solid transparent;\n}\n\n.parameter:hover {\n  background: rgba(255, 255, 255, 0.25);\n  border-color: rgba(255, 255, 255, 0.5);\n  transform: translateY(-2px);\n}\n\n.param-icon {\n  font-size: 28px;\n  margin-bottom: 8px;\n}\n\n.param-label {\n  font-size: 12px;\n  opacity: 0.8;\n  text-transform: uppercase;\n  font-weight: 600;\n  letter-spacing: 0.5px;\n}\n\n.param-value {\n  font-size: 20px;\n  font-weight: 700;\n  margin-top: 5px;\n}\n\n.modal {\n  display: none;\n  position: fixed;\n  z-index: 1000;\n  left: 0;\n  top: 0;\n  width: 100%;\n  height: 100%;\n  background-color: rgba(0, 0, 0, 0.5);\n  border-radius: 10px;\n}\n\n.modal-content {\n  background-color: white;\n  margin: 10% auto;\n  padding: 30px;\n  border-radius: 15px;\n  width: 90%;\n  max-width: 500px;\n  box-shadow: 0 12px 40px rgba(0, 0, 0, 0.3);\n  color: #333;\n}\n\n.modal-header {\n  display: flex;\n  justify-content: space-between;\n  align-items: center;\n  margin-bottom: 20px;\n  border-bottom: 2px solid #667eea;\n  padding-bottom: 15px;\n}\n\n.modal-title {\n  font-size: 22px;\n  font-weight: 700;\n  color: #667eea;\n}\n\n.close-btn {\n  font-size: 28px;\n  font-weight: bold;\n  color: #999;\n  cursor: pointer;\n  background: none;\n  border: none;\n  padding: 0;\n}\n\n.close-btn:hover {\n  color: #333;\n}\n\n.modal-body {\n  font-size: 16px;\n  line-height: 1.6;\n  color: #555;\n}\n\n.modal-body p {\n  margin: 10px 0;\n}\n\n.info-link {\n  color: #667eea;\n  text-decoration: none;\n  font-weight: 600;\n}\n\n.info-link:hover {\n  text-decoration: underline;\n}\n\n.field-alert {\n  background: #fff3cd;\n  border-left: 4px solid #ffc107;\n  padding: 12px;\n  margin-top: 15px;\n  border-radius: 5px;\n  font-size: 14px;\n  color: #856404;\n}\n\n.favorable {\n  background: #d4edda;\n  border-left-color: #28a745;\n  color: #155724;\n}\n\n.caution {\n  background: #fff3cd;\n  border-left-color: #ffc107;\n  color: #856404;\n}\n\n.warning {\n  background: #f8d7da;\n  border-left-color: #dc3545;\n  color: #721c24;\n}\n\n.source-info {\n  text-align: center;\n  font-size: 12px;\n  opacity: 0.9;\n  margin-top: 15px;\n  padding-top: 15px;\n  border-top: 1px solid rgba(255, 255, 255, 0.3);\n}\n</style>\n\n<div class=\"weather-widget\">\n  <div class=\"weather-header\">\n    <div class=\"location-info\">\n      <h2>🌊 Coastal Tanzania</h2>\n      <p class=\"update-time\">Northeast Monsoon (Kaskazi)<br>Updated: Today</p>\n    </div>\n  </div>\n\n  <div class=\"weather-main\">\n    <div>\n      <div class=\"temperature-display\">26°C</div>\n      <div class=\"weather-condition\">Partly Cloudy</div>\n    </div>\n    <div class=\"weather-icon\">⛅</div>\n  </div>\n\n  <div class=\"weather-parameters\">\n    <div class=\"parameter\" onclick=\"openModal('wind')\">\n      <div class=\"param-icon\">💨</div>\n      <div class=\"param-label\">Wind</div>\n      <div class=\"param-value\">15 knots</div>\n    </div>\n\n    <div class=\"parameter\" onclick=\"openModal('waves')\">\n      <div class=\"param-icon\">🌊</div>\n      <div class=\"param-label\">Wave Height</div>\n      <div class=\"param-value\">0.8m</div>\n    </div>\n\n    <div class=\"parameter\" onclick=\"openModal('temp')\">\n      <div class=\"param-icon\">🌡️</div>\n      <div class=\"param-label\">Sea Temp</div>\n      <div class=\"param-value\">25°C</div>\n    </div>\n\n    <div class=\"parameter\" onclick=\"openModal('visibility')\">\n      <div class=\"param-icon\">👁️</div>\n      <div class=\"param-label\">Visibility</div>\n      <div class=\"param-value\">Excellent</div>\n    </div>\n\n    <div class=\"parameter\" onclick=\"openModal('humidity')\">\n      <div class=\"param-icon\">💧</div>\n      <div class=\"param-label\">Humidity</div>\n      <div class=\"param-value\">75%</div>\n    </div>\n\n    <div class=\"parameter\" onclick=\"openModal('pressure')\">\n      <div class=\"param-icon\">🔽</div>\n      <div class=\"param-label\">Pressure</div>\n      <div class=\"param-value\">1013 mb</div>\n    </div>\n  </div>\n\n  <div class=\"field-alert favorable\">\n    ✅ <strong>Field Operations Status:</strong> EXCELLENT - Optimal conditions for coastal surveys and marine activities\n  </div>\n\n  <div class=\"source-info\">\n    Data reflects typical Northeast Monsoon season conditions (Dec 2025 - Mar 2026)<br>\n    <a href=\"news.qmd\" class=\"info-link\">View detailed seasonal information</a>\n  </div>\n</div>\n\n<!-- Modals for each parameter -->\n\n<!-- Wind Modal -->\n<div id=\"windModal\" class=\"modal\">\n  <div class=\"modal-content\">\n    <div class=\"modal-header\">\n      <span class=\"modal-title\">💨 Wind Conditions</span>\n      <button class=\"close-btn\" onclick=\"closeModal('wind')\">&times;</button>\n    </div>\n    <div class=\"modal-body\">\n      <p><strong>Current Speed:</strong> 15 knots (28 km/h)</p>\n      <p><strong>Direction:</strong> Northeast (Kaskazi)</p>\n      <p><strong>Gusts:</strong> Up to 20 knots</p>\n      <p><strong>Optimal for Operations:</strong> Yes</p>\n      <div class=\"field-alert favorable\">\n        Northeast monsoon winds are predictable and favorable for vessel operations and fieldwork during this season.\n      </div>\n      <p style=\"margin-top: 15px; font-size: 13px;\">\n        <a href=\"https://www.ncei.noaa.gov/products/ocean-weather-forecast\" class=\"info-link\" target=\"_blank\">\n          View detailed wind forecasts →\n        </a>\n      </p>\n    </div>\n  </div>\n</div>\n\n<!-- Wave Height Modal -->\n<div id=\"wavesModal\" class=\"modal\">\n  <div class=\"modal-content\">\n    <div class=\"modal-header\">\n      <span class=\"modal-title\">🌊 Wave Conditions</span>\n      <button class=\"close-btn\" onclick=\"closeModal('waves')\">&times;</button>\n    </div>\n    <div class=\"modal-body\">\n      <p><strong>Significant Wave Height:</strong> 0.8m (calm)</p>\n      <p><strong>Maximum Wave Height:</strong> 1.5m</p>\n      <p><strong>Period:</strong> 6-8 seconds</p>\n      <p><strong>Optimal for Survey Vessels:</strong> Yes</p>\n      <div class=\"field-alert favorable\">\n        Current conditions are ideal for biodiversity surveys, ecosystem monitoring, and community engagement activities. Water conditions are safe for field operations.\n      </div>\n      <p style=\"margin-top: 15px; font-size: 13px;\">\n        <a href=\"https://www.ndbc.noaa.gov/\" class=\"info-link\" target=\"_blank\">\n          View real-time buoy data →\n        </a>\n      </p>\n    </div>\n  </div>\n</div>\n\n<!-- Sea Temperature Modal -->\n<div id=\"tempModal\" class=\"modal\">\n  <div class=\"modal-content\">\n    <div class=\"modal-header\">\n      <span class=\"modal-title\">🌡️ Sea Temperature</span>\n      <button class=\"close-btn\" onclick=\"closeModal('temp')\">&times;</button>\n    </div>\n    <div class=\"modal-body\">\n      <p><strong>Surface Temperature:</strong> 25°C</p>\n      <p><strong>Typical Range:</strong> 24-26°C during Northeast Monsoon</p>\n      <p><strong>Stability:</strong> Moderate to stable</p>\n      <p><strong>Ecosystem Impact:</strong> Favorable for marine surveys</p>\n      <div class=\"field-alert favorable\">\n        Stable sea temperatures support marine biodiversity assessment and ecosystem monitoring. Excellent conditions for both field sampling and community engagement in coastal areas.\n      </div>\n      <p style=\"margin-top: 15px; font-size: 13px;\">\n        <a href=\"news.qmd#current-conditions--field-operations\" class=\"info-link\">\n          View full seasonal analysis →\n        </a>\n      </p>\n    </div>\n  </div>\n</div>\n\n<!-- Visibility Modal -->\n<div id=\"visibilityModal\" class=\"modal\">\n  <div class=\"modal-content\">\n    <div class=\"modal-header\">\n      <span class=\"modal-title\">👁️ Visibility & Sky Conditions</span>\n      <button class=\"close-btn\" onclick=\"closeModal('visibility')\">&times;</button>\n    </div>\n    <div class=\"modal-body\">\n      <p><strong>Visibility:</strong> Excellent (&gt;10 km)</p>\n      <p><strong>Cloud Cover:</strong> Partly cloudy (40%)</p>\n      <p><strong>Sky Condition:</strong> Mostly clear</p>\n      <p><strong>Precipitation Probability:</strong> 10%</p>\n      <div class=\"field-alert favorable\">\n        Excellent visibility is ideal for remote sensing activities, aerial surveys, and visual ecosystem assessment. Low precipitation probability supports outdoor field activities.\n      </div>\n      <p style=\"margin-top: 15px; font-size: 13px;\">\n        <a href=\"https://www.wunderground.com/\" class=\"info-link\" target=\"_blank\">\n          Check detailed forecasts →\n        </a>\n      </p>\n    </div>\n  </div>\n</div>\n\n<!-- Humidity Modal -->\n<div id=\"humidityModal\" class=\"modal\">\n  <div class=\"modal-content\">\n    <div class=\"modal-header\">\n      <span class=\"modal-title\">💧 Humidity Levels</span>\n      <button class=\"close-btn\" onclick=\"closeModal('humidity')\">&times;</button>\n    </div>\n    <div class=\"modal-body\">\n      <p><strong>Relative Humidity:</strong> 75%</p>\n      <p><strong>Dew Point:</strong> 20°C</p>\n      <p><strong>Comfort Level:</strong> Moderate</p>\n      <p><strong>Equipment Impact:</strong> Manageable</p>\n      <div class=\"field-alert caution\">\n        Moderate humidity is typical for coastal areas. Ensure proper care for electronic equipment and maintain hydration during field operations. Use protective covers for sensitive instruments.\n      </div>\n      <p style=\"margin-top: 15px; font-size: 13px;\">\n        Recommended: UV-protected field clothing and equipment maintenance protocols.\n      </p>\n    </div>\n  </div>\n</div>\n\n<!-- Pressure Modal -->\n<div id=\"pressureModal\" class=\"modal\">\n  <div class=\"modal-content\">\n    <div class=\"modal-header\">\n      <span class=\"modal-title\">🔽 Atmospheric Pressure</span>\n      <button class=\"close-btn\" onclick=\"closeModal('pressure')\">&times;</button>\n    </div>\n    <div class=\"modal-body\">\n      <p><strong>Current Pressure:</strong> 1013 mb</p>\n      <p><strong>Trend:</strong> Stable</p>\n      <p><strong>Interpretation:</strong> Fair weather conditions</p>\n      <p><strong>Weather Stability:</strong> Expected to remain stable</p>\n      <div class=\"field-alert favorable\">\n        Stable atmospheric pressure indicates predictable weather patterns. Excellent conditions for planning multi-day field campaigns and stakeholder engagement activities.\n      </div>\n      <p style=\"margin-top: 15px; font-size: 13px;\">\n        No significant weather systems approaching coastal Tanzania.\n      </p>\n    </div>\n  </div>\n</div>\n\n<script>\nfunction openModal(param) {\n  const modalId = param + 'Modal';\n  document.getElementById(modalId).style.display = 'block';\n}\n\nfunction closeModal(param) {\n  const modalId = param + 'Modal';\n  document.getElementById(modalId).style.display = 'none';\n}\n\n// Close modal when clicking outside of it\nwindow.onclick = function(event) {\n  if (event.target.classList.contains('modal')) {\n    event.target.style.display = 'none';\n  }\n}\n</script>\n```\n"},"formats":{"html":{"identifier":{"display-name":"HTML","target-format":"html","base-format":"html"},"execute":{"fig-width":7,"fig-height":5,"fig-format":"retina","fig-dpi":96,"df-print":"default","error":false,"eval":true,"cache":null,"freeze":"auto","echo":true,"output":true,"warning":true,"include":true,"keep-md":false,"keep-ipynb":false,"ipynb":null,"enabled":null,"daemon":null,"daemon-restart":false,"debug":false,"ipynb-filters":[],"ipynb-shell-interactivity":null,"plotly-connected":true,"engine":"markdown"},"render":{"keep-tex":false,"keep-typ":false,"keep-source":false,"keep-hidden":false,"prefer-html":false,"output-divs":true,"output-ext":"html","fig-align":"default","fig-pos":null,"fig-env":null,"code-fold":true,"code-overflow":"scroll","code-link":false,"code-line-numbers":false,"code-tools":false,"tbl-colwidths":"auto","merge-includes":true,"inline-includes":false,"preserve-yaml":false,"latex-auto-mk":true,"latex-auto-install":true,"latex-clean":true,"latex-min-runs":1,"latex-max-runs":10,"latex-makeindex":"makeindex","latex-makeindex-opts":[],"latex-tlmgr-opts":[],"latex-input-paths":[],"latex-output-dir":null,"link-external-icon":true,"link-external-newwindow":true,"self-contained-math":false,"format-resources":[],"notebook-links":true},"pandoc":{"standalone":true,"wrap":"none","default-image-extension":"png","to":"html","css":["styles.css"],"toc":false,"toc-depth":2,"highlight-style":"atom-one","include-after-body":{"text":"<button class=\"scroll-to-top\" id=\"scrollToTopBtn\" onclick=\"scrollToTop()\">↑</button>\n<script>\n  const scrollBtn = document.getElementById('scrollToTopBtn');\n  \n  // Translation dictionary\n  const translations = {\n    en: {\n      'nav.home': 'Home',\n      'nav.about': 'About',\n      'nav.why_lmsp': 'Why LMSP',\n      'nav.initiatives': 'LMSP Initiatives',\n      'nav.ongoing': 'Ongoing',\n      'nav.planned': 'Planned',\n      'nav.completed': 'Completed',\n      'nav.blog': 'Blog',\n      'nav.resources': 'Resource',\n      'nav.implementation_guide': 'Implementation Guide',\n      'nav.books_articles': 'Book and Articles',\n      'nav.case_studies': 'Case Studies',\n      'nav.team': 'Team',\n      'nav.contacts': 'Contacts',\n      'nav.admin': 'Admin',\n      'nav.archive': 'Archive',\n      'ui.comments_title': 'Comments & Discussion',\n      'ui.comments_info': 'Join the conversation! Share your thoughts and feedback below.',\n      'ui.name': 'Name',\n      'ui.email': 'Email',\n      'ui.comment': 'Comment',\n      'ui.post_comment': 'Post Comment',\n      'ui.no_comments': 'No comments yet. Be the first to share your thoughts!',\n      'footer.quick_links': 'QUICK LINKS',\n      'footer.contact_us': 'Contact Us',\n      'footer.tools': 'Tools',\n      'lang.name': 'English'\n    },\n    sw: {\n      'nav.home': 'Nyumbani',\n      'nav.about': 'Kuhusu',\n      'nav.why_lmsp': 'Kwa Nini LMSP',\n      'nav.initiatives': 'Mpango wa LMSP',\n      'nav.ongoing': 'Inaendelea',\n      'nav.planned': 'Iliyopangwa',\n      'nav.completed': 'Imekamilika',\n      'nav.blog': 'Blogi',\n      'nav.resources': 'Rasilimali',\n      'nav.implementation_guide': 'Mwongozo wa Utekelezaji',\n      'nav.books_articles': 'Vitabu na Makala',\n      'nav.case_studies': 'Masomo ya Kesi',\n      'nav.team': 'Timu',\n      'nav.contacts': 'Wasiliani',\n      'nav.admin': 'Msimamizi',\n      'nav.archive': 'Hifadhi',\n      'ui.comments_title': 'Maoni & Mijadala',\n      'ui.comments_info': 'Jiunge na mazungumzo! Shiriki mawazo yako na maoni hapa chini.',\n      'ui.name': 'Jina',\n      'ui.email': 'Barua pepe',\n      'ui.comment': 'Maoni',\n      'ui.post_comment': 'Chapisha Maoni',\n      'ui.no_comments': 'Hakuna maoni bado. Kuwa wa kwanza kugawana mawazo yako!',\n      'footer.quick_links': 'VIUNGO VYA HARAKA',\n      'footer.contact_us': 'Wasiliana Nasi',\n      'footer.tools': 'Zana',\n      'lang.name': 'Kiswahili'\n    }\n  };\n  \n  // Simple language switcher\n  function initLanguageSwitcher() {\n    const currentLang = localStorage.getItem('lmsp_language') || 'en';\n    \n    // Create switcher HTML\n    const switcherHTML = `\n      <div id=\"lang-switcher\" style=\"display: inline-block; margin-left: 10px;\">\n        <button id=\"lang-btn\" style=\"background: none; border: none; color: white; cursor: pointer; font-size: 16px; padding: 5px 10px;\">\n          🌐 <span id=\"lang-text\">${translations[currentLang]['lang.name']}</span>\n        </button>\n        <div id=\"lang-menu\" style=\"position: absolute; top: 100%; right: 0; background: white; border: 1px solid #ddd; border-radius: 4px; min-width: 150px; display: none; z-index: 1000; box-shadow: 0 2px 8px rgba(0,0,0,0.1);\">\n          <button class=\"lang-opt\" data-lang=\"en\" style=\"width: 100%; padding: 10px; border: none; background: none; text-align: left; cursor: pointer; font-size: 14px;\">🇬🇧 English</button>\n          <button class=\"lang-opt\" data-lang=\"sw\" style=\"width: 100%; padding: 10px; border: none; background: none; text-align: left; cursor: pointer; font-size: 14px;\">🇹🇿 Kiswahili</button>\n        </div>\n      </div>\n    `;\n    \n    // Find navbar and insert switcher\n    setTimeout(() => {\n      const navbar = document.querySelector('.navbar') || document.querySelector('nav');\n      if (navbar) {\n        const navRight = navbar.querySelector('.navbar-nav') || navbar;\n        if (navRight) {\n          navRight.insertAdjacentHTML('beforeend', switcherHTML);\n          setupLanguageSwitcherEvents();\n        }\n      }\n    }, 500);\n  }\n  \n  function setupLanguageSwitcherEvents() {\n    const btn = document.getElementById('lang-btn');\n    const menu = document.getElementById('lang-menu');\n    const options = document.querySelectorAll('.lang-opt');\n    \n    if (!btn || !menu) return;\n    \n    btn.addEventListener('click', (e) => {\n      e.stopPropagation();\n      menu.style.display = menu.style.display === 'none' ? 'block' : 'none';\n    });\n    \n    options.forEach(opt => {\n      opt.addEventListener('click', (e) => {\n        e.stopPropagation();\n        const lang = opt.getAttribute('data-lang');\n        changeLanguage(lang);\n        menu.style.display = 'none';\n      });\n    });\n    \n    document.addEventListener('click', () => {\n      menu.style.display = 'none';\n    });\n  }\n  \n  function changeLanguage(lang) {\n    localStorage.setItem('lmsp_language', lang);\n    document.documentElement.lang = lang;\n    \n    // Update all elements with data-i18n\n    document.querySelectorAll('[data-i18n]').forEach(el => {\n      const key = el.getAttribute('data-i18n');\n      if (translations[lang] && translations[lang][key]) {\n        el.textContent = translations[lang][key];\n      }\n    });\n    \n    // Update language indicator\n    const langText = document.getElementById('lang-text');\n    if (langText) {\n      langText.textContent = translations[lang]['lang.name'];\n    }\n  }\n  \n  // Show/hide scroll button based on scroll position\n  window.addEventListener('scroll', () => {\n    if (window.scrollY > 300) {\n      scrollBtn.classList.add('show');\n    } else {\n      scrollBtn.classList.remove('show');\n    }\n  });\n  \n  // Scroll to top smoothly\n  function scrollToTop() {\n    window.scrollTo({\n      top: 0,\n      behavior: 'smooth'\n    });\n  }\n  \n  // Alternative: keyboard shortcut (Press Home key to go to top)\n  document.addEventListener('keydown', (e) => {\n    if (e.key === 'Home') {\n      e.preventDefault();\n      scrollToTop();\n    }\n  });\n  \n  // TOC Collapse Feature\n  document.addEventListener('DOMContentLoaded', function() {\n    const tocTitle = document.getElementById('toc-title');\n    const tocContainer = document.querySelector('nav#TOC');\n    const tocList = document.querySelector('nav#TOC > ul');\n    \n    if (tocTitle && tocList && tocContainer) {\n      // Create toggle button\n      const toggleBtn = document.createElement('button');\n      toggleBtn.className = 'toc-toggle-btn';\n      toggleBtn.innerHTML = '📖';\n      toggleBtn.setAttribute('aria-label', 'Toggle table of contents');\n      toggleBtn.setAttribute('title', 'Collapse table of contents');\n      \n      // Insert button next to title\n      tocTitle.parentNode.insertBefore(toggleBtn, tocTitle.nextSibling);\n      \n      // Load saved state from localStorage\n      const savedState = localStorage.getItem('toc-collapsed');\n      if (savedState === 'true') {\n        tocList.classList.add('toc-collapsed');\n        toggleBtn.innerHTML = '📕';\n        toggleBtn.setAttribute('title', 'Expand table of contents');\n      }\n      \n      // Toggle functionality\n      toggleBtn.addEventListener('click', function(e) {\n        e.preventDefault();\n        tocList.classList.toggle('toc-collapsed');\n        const isCollapsed = tocList.classList.contains('toc-collapsed');\n        toggleBtn.innerHTML = isCollapsed ? '📕' : '📖';\n        toggleBtn.setAttribute('title', isCollapsed ? 'Expand table of contents' : 'Collapse table of contents');\n        localStorage.setItem('toc-collapsed', isCollapsed);\n      });\n    }\n  });\n  \n  // Blog Category Filter\n  document.addEventListener('DOMContentLoaded', function() {\n    const categoryContainer = document.getElementById('categoryTags');\n    if (!categoryContainer) return;\n    \n    // Collect all categories from post metadata\n    const categories = new Set();\n    const postItems = document.querySelectorAll('.quarto-grid-item');\n    \n    postItems.forEach(item => {\n      const categoryElements = item.querySelectorAll('.listing-category');\n      categoryElements.forEach(cat => {\n        if (cat.textContent.trim()) {\n          categories.add(cat.textContent.trim());\n        }\n      });\n    });\n    \n    // Create filter tags\n    const categoriesArray = Array.from(categories).sort();\n    \n    // Add \"All\" button\n    const allTag = document.createElement('button');\n    allTag.className = 'category-tag active';\n    allTag.textContent = 'All Posts';\n    allTag.setAttribute('data-category', 'all');\n    categoryContainer.appendChild(allTag);\n    \n    // Add category tags\n    categoriesArray.forEach(cat => {\n      const tag = document.createElement('button');\n      tag.className = 'category-tag';\n      tag.textContent = cat;\n      tag.setAttribute('data-category', cat);\n      categoryContainer.appendChild(tag);\n    });\n    \n    // Filter functionality\n    categoryContainer.addEventListener('click', function(e) {\n      if (!e.target.classList.contains('category-tag')) return;\n      \n      const selectedCategory = e.target.getAttribute('data-category');\n      \n      // Update active state\n      document.querySelectorAll('.category-tag').forEach(tag => {\n        tag.classList.remove('active');\n      });\n      e.target.classList.add('active');\n      \n      // Filter posts\n      postItems.forEach(item => {\n        if (selectedCategory === 'all') {\n          item.style.display = '';\n        } else {\n          const itemCategories = Array.from(item.querySelectorAll('.listing-category'))\n            .map(cat => cat.textContent.trim());\n          \n          if (itemCategories.includes(selectedCategory)) {\n            item.style.display = '';\n          } else {\n            item.style.display = 'none';\n          }\n        }\n      });\n    });\n  });\n  \n  // Comments Section - Custom Form\n  document.addEventListener('DOMContentLoaded', function() {\n    // Check if comments are disabled on this page\n    const isCommentsDisabled = document.querySelector('meta[name=\"comments\"]')?.getAttribute('content') === 'false' ||\n                               document.body.classList.contains('no-comments');\n    \n    if (isCommentsDisabled) return; // Skip adding comments if disabled\n    \n    const mainContent = document.querySelector('main') || document.querySelector('.quarto-page-body');\n    \n    if (mainContent) {\n      // Create comments container\n      const commentsSection = document.createElement('section');\n      commentsSection.className = 'comments-section';\n      commentsSection.innerHTML = `\n        <div class=\"comments-wrapper\">\n          <h2>Comments & Discussion</h2>\n          <p class=\"comments-info\">Join the conversation! Share your thoughts and feedback below.</p>\n          \n          <div class=\"comment-form\">\n            <form id=\"commentForm\">\n              <div class=\"form-group\">\n                <label for=\"commentName\">Name *</label>\n                <input type=\"text\" id=\"commentName\" name=\"name\" required>\n              </div>\n              \n              <div class=\"form-group\">\n                <label for=\"commentEmail\">Email *</label>\n                <input type=\"email\" id=\"commentEmail\" name=\"email\" required>\n              </div>\n              \n              <div class=\"form-group\">\n                <label for=\"commentText\">Comment *</label>\n                <textarea id=\"commentText\" name=\"comment\" rows=\"5\" required></textarea>\n              </div>\n              \n              <button type=\"submit\" class=\"btn btn-primary\">Post Comment</button>\n            </form>\n          </div>\n          \n          <div id=\"commentsDisplay\" class=\"comments-display\">\n            <p class=\"no-comments\">No comments yet. Be the first to share your thoughts!</p>\n          </div>\n        </div>\n      `;\n      \n      // Append to end of main content\n      mainContent.appendChild(commentsSection);\n      \n      // Load comments from localStorage\n      loadComments();\n      \n      // Handle form submission\n      document.getElementById('commentForm').addEventListener('submit', function(e) {\n        e.preventDefault();\n        \n        const name = document.getElementById('commentName').value;\n        const email = document.getElementById('commentEmail').value;\n        const text = document.getElementById('commentText').value;\n        \n        if (name && email && text) {\n          const comment = {\n            name: name,\n            email: email,\n            text: text,\n            date: new Date().toLocaleString(),\n            id: Date.now()\n          };\n          \n          // Save comment to localStorage\n          let comments = JSON.parse(localStorage.getItem('pageComments') || '[]');\n          comments.push(comment);\n          localStorage.setItem('pageComments', JSON.stringify(comments));\n          \n          // Clear form\n          this.reset();\n          \n          // Reload comments display\n          loadComments();\n        }\n      });\n      \n      function loadComments() {\n        const comments = JSON.parse(localStorage.getItem('pageComments') || '[]');\n        const display = document.getElementById('commentsDisplay');\n        \n        if (comments.length === 0) {\n          display.innerHTML = '<p class=\"no-comments\">No comments yet. Be the first to share your thoughts!</p>';\n        } else {\n          display.innerHTML = comments.map(c => `\n            <div class=\"comment-item\">\n              <div class=\"comment-header\">\n                <strong>${escapeHtml(c.name)}</strong>\n                <span class=\"comment-date\">${c.date}</span>\n              </div>\n              <p class=\"comment-text\">${escapeHtml(c.text).replace(/\\n/g, '<br>')}</p>\n            </div>\n          `).join('');\n        }\n      }\n      \n      function escapeHtml(text) {\n        const div = document.createElement('div');\n        div.textContent = text;\n        return div.innerHTML;\n      }\n    }\n  });\n  \n  // Statistics Cards - Count Up Animation\n  document.addEventListener('DOMContentLoaded', function() {\n    const statCards = document.querySelectorAll('.stats-card h3');\n    const animationDuration = 10000; // 10 seconds in milliseconds\n    const updateInterval = 33; // Update every 33ms for smooth animation\n    const totalFrames = Math.floor(animationDuration / updateInterval);\n    \n    statCards.forEach(card => {\n      const finalValue = parseInt(card.textContent);\n      if (!isNaN(finalValue)) {\n        let currentFrame = 0;\n        \n        const counter = setInterval(() => {\n          currentFrame++;\n          // Easing: linear progress from 0 to finalValue over 10 seconds\n          const currentValue = Math.floor((currentFrame / totalFrames) * finalValue);\n          \n          if (currentFrame >= totalFrames) {\n            card.textContent = finalValue + '+';\n            clearInterval(counter);\n          } else {\n            card.textContent = currentValue + '+';\n          }\n        }, updateInterval);\n      }\n    });\n  });\n  \n  // Reading Time Estimate\n  document.addEventListener('DOMContentLoaded', function() {\n    const article = document.querySelector('main') || document.querySelector('.quarto-page-body');\n    \n    if (article) {\n      // Get text content from article\n      const text = article.innerText;\n      \n      // Calculate word count\n      const wordCount = text.trim().split(/\\s+/).length;\n      \n      // Average reading speed: 200 words per minute\n      const readingSpeed = 200;\n      const readingTime = Math.ceil(wordCount / readingSpeed);\n      \n      // Only show if there's substantial content (>100 words)\n      if (wordCount > 100) {\n        // Create reading time badge\n        const readingTimeBadge = document.createElement('div');\n        readingTimeBadge.className = 'reading-time-badge';\n        readingTimeBadge.innerHTML = `\n          <span class=\"reading-time-icon\">⏱️</span>\n          <span class=\"reading-time-text\">${readingTime} min read</span>\n        `;\n        \n        // Insert after page title\n        const pageTitle = document.querySelector('h1');\n        if (pageTitle && pageTitle.parentNode) {\n          pageTitle.parentNode.insertBefore(readingTimeBadge, pageTitle.nextSibling);\n        }\n      }\n      \n      // Create share buttons\n      const pageTitle = document.querySelector('h1');\n      const pageUrl = window.location.href;\n      const pageText = pageTitle ? pageTitle.textContent : document.title;\n      \n      const shareButtons = document.createElement('div');\n      shareButtons.className = 'share-buttons';\n      shareButtons.innerHTML = `\n        <span class=\"share-label\">Share:</span>\n        <a href=\"https://twitter.com/intent/tweet?url=${encodeURIComponent(pageUrl)}&text=${encodeURIComponent(pageText)}\" \n           class=\"share-btn share-twitter\" \n           target=\"_blank\" \n           rel=\"noopener noreferrer\"\n           title=\"Share on Twitter\">\n          𝕏\n        </a>\n        <a href=\"https://www.linkedin.com/sharing/share-offsite/?url=${encodeURIComponent(pageUrl)}\" \n           class=\"share-btn share-linkedin\" \n           target=\"_blank\" \n           rel=\"noopener noreferrer\"\n           title=\"Share on LinkedIn\">\n          in\n        </a>\n        <a href=\"mailto:?subject=${encodeURIComponent(pageText)}&body=${encodeURIComponent(pageUrl)}\" \n           class=\"share-btn share-email\" \n           title=\"Share via Email\">\n          ✉️\n        </a>\n      `;\n      \n      if (pageTitle && pageTitle.parentNode) {\n        pageTitle.parentNode.insertBefore(shareButtons, pageTitle.nextSibling.nextSibling);\n      }\n    }\n  });\n</script>\n"},"output-file":"weather.html"},"language":{"toc-title-document":"Table of contents","toc-title-website":"On this page","related-formats-title":"Other Formats","related-notebooks-title":"Notebooks","source-notebooks-prefix":"Source","other-links-title":"Other Links","code-links-title":"Code Links","launch-dev-container-title":"Launch Dev Container","launch-binder-title":"Launch Binder","article-notebook-label":"Article Notebook","notebook-preview-download":"Download Notebook","notebook-preview-download-src":"Download Source","notebook-preview-back":"Back to Article","manuscript-meca-bundle":"MECA Bundle","section-title-abstract":"Abstract","section-title-appendices":"Appendices","section-title-footnotes":"Footnotes","section-title-references":"References","section-title-reuse":"Reuse","section-title-copyright":"Copyright","section-title-citation":"Citation","appendix-attribution-cite-as":"For attribution, please cite this work as:","appendix-attribution-bibtex":"BibTeX citation:","appendix-view-license":"View License","title-block-author-single":"Author","title-block-author-plural":"Authors","title-block-affiliation-single":"Affiliation","title-block-affiliation-plural":"Affiliations","title-block-published":"Published","title-block-modified":"Modified","title-block-keywords":"Keywords","callout-tip-title":"Tip","callout-note-title":"Note","callout-warning-title":"Warning","callout-important-title":"Important","callout-caution-title":"Caution","code-summary":"Code","code-tools-menu-caption":"Code","code-tools-show-all-code":"Show All Code","code-tools-hide-all-code":"Hide All Code","code-tools-view-source":"View Source","code-tools-source-code":"Source Code","tools-share":"Share","tools-download":"Download","code-line":"Line","code-lines":"Lines","copy-button-tooltip":"Copy to Clipboard","copy-button-tooltip-success":"Copied!","repo-action-links-edit":"Edit this page","repo-action-links-source":"View source","repo-action-links-issue":"Report an issue","back-to-top":"Back to top","search-no-results-text":"No results","search-matching-documents-text":"matching documents","search-copy-link-title":"Copy link to search","search-hide-matches-text":"Hide additional matches","search-more-match-text":"more match in this document","search-more-matches-text":"more matches in this document","search-clear-button-title":"Clear","search-text-placeholder":"","search-detached-cancel-button-title":"Cancel","search-submit-button-title":"Submit","search-label":"Search","toggle-section":"Toggle section","toggle-sidebar":"Toggle sidebar navigation","toggle-dark-mode":"Toggle dark mode","toggle-reader-mode":"Toggle reader mode","toggle-navigation":"Toggle navigation","crossref-fig-title":"Figure","crossref-tbl-title":"Table","crossref-lst-title":"Listing","crossref-thm-title":"Theorem","crossref-lem-title":"Lemma","crossref-cor-title":"Corollary","crossref-prp-title":"Proposition","crossref-cnj-title":"Conjecture","crossref-def-title":"Definition","crossref-exm-title":"Example","crossref-exr-title":"Exercise","crossref-ch-prefix":"Chapter","crossref-apx-prefix":"Appendix","crossref-sec-prefix":"Section","crossref-eq-prefix":"Equation","crossref-lof-title":"List of Figures","crossref-lot-title":"List of Tables","crossref-lol-title":"List of Listings","environment-proof-title":"Proof","environment-remark-title":"Remark","environment-solution-title":"Solution","listing-page-order-by":"Order By","listing-page-order-by-default":"Default","listing-page-order-by-date-asc":"Oldest","listing-page-order-by-date-desc":"Newest","listing-page-order-by-number-desc":"High to Low","listing-page-order-by-number-asc":"Low to High","listing-page-field-date":"Date","listing-page-field-title":"Title","listing-page-field-description":"Description","listing-page-field-author":"Author","listing-page-field-filename":"File Name","listing-page-field-filemodified":"Modified","listing-page-field-subtitle":"Subtitle","listing-page-field-readingtime":"Reading Time","listing-page-field-wordcount":"Word Count","listing-page-field-categories":"Categories","listing-page-minutes-compact":"{0} min","listing-page-category-all":"All","listing-page-no-matches":"No matching items","listing-page-words":"{0} words","listing-page-filter":"Filter","draft":"Draft"},"metadata":{"lang":"en","fig-responsive":true,"quarto-version":"1.6.39","theme":"cosmo","toc-location":"right","page-layout":"full","title":"Live Weather"},"extensions":{"book":{"multiFile":true}}}},"projectFormats":["html"]}